discordbot/__init__.py
discordbot/admin.py
discordbot/apps.py
discordbot/bot.py
discordbot/config.py
discordbot/errors.py
discordbot/models.py
discordbot/tests.py
discordbot/urls.py
discordbot/utils.py
discordbot/views.py
discordbot/botcmds/__init__.py
discordbot/botcmds/_preset.py
discordbot/botcmds/basic.py
discordbot/botcmds/channels.py
discordbot/botcmds/converters.py
discordbot/botcmds/domains.py
discordbot/botcmds/embedgenerator.py
discordbot/botcmds/games.py
discordbot/botcmds/help.py
discordbot/botcmds/moderation.py
discordbot/botcmds/music.py
discordbot/botcmds/notifier.py
discordbot/botcmds/owneronly.py
discordbot/botcmds/polls.py
discordbot/botcmds/support.py
discordbot/botcmds/userinfo.py
discordbot/botevents/__init__.py
discordbot/botevents/general.py
discordbot/botevents/on_command.py
discordbot/botevents/on_command_error.py
discordbot/botevents/on_message.py
discordbot/botmodules/__init__.py
discordbot/botmodules/apis.py
discordbot/botmodules/audio.py
discordbot/botmodules/bots.py
discordbot/botmodules/converters.py
discordbot/botmodules/parser.py
discordbot/botmodules/serverdata.py
discordbot/management/commands/run-discordbot.py
discordbot/migrations/0001_initial.py
discordbot/migrations/0002_auto_20200701_1655.py
discordbot/migrations/0003_amongusgame.py
discordbot/migrations/0004_auto_20201022_0928.py
discordbot/migrations/0005_amongusgame_text_message_id.py
discordbot/migrations/0006_auto_20201022_1804.py
discordbot/migrations/0007_auto_20201023_2145.py
discordbot/migrations/0008_amongusgame_last_tracking_data.py
discordbot/migrations/0009_remove_amongusgame_tracker_connected.py
discordbot/migrations/0010_viergewinntgame.py
discordbot/migrations/0011_auto_20201031_1721.py
discordbot/migrations/0012_botpermission.py
discordbot/migrations/0013_notifiersub.py
discordbot/migrations/0014_auto_20201110_1826.py
discordbot/migrations/0015_notifiersub_name.py
discordbot/migrations/0016_auto_20201113_2031.py
discordbot/migrations/0017_audiosource.py
django_discordbot-1.2.7.dist-info/LICENSE
django_discordbot-1.2.7.dist-info/METADATA
django_discordbot-1.2.7.dist-info/WHEEL
django_discordbot-1.2.7.dist-info/top_level.txt
django_discordbot-1.2.7.dist-info/RECORD
