Metadata-Version: 2.1
Name: django-discordbot
Version: 1.2.7
Summary: Ein Discordbot für Django
Home-page: https://github.com/rafaelurben/django-discordbot/
Author: Rafael Urben
Author-email: github@rafaelurben.ch
License: MIT
Project-URL: GitHub, https://github.com/rafaelurben/django-discordbot
Project-URL: Issues, https://github.com/rafaelurben/django-discordbot/issues
Platform: UNKNOWN
Classifier: Environment :: Web Environment
Classifier: Framework :: Django
Classifier: Framework :: Django :: 3.2
Classifier: Intended Audience :: Developers
Classifier: License :: OSI Approved :: MIT License
Classifier: Operating System :: OS Independent
Classifier: Programming Language :: Python
Classifier: Programming Language :: Python :: 3
Classifier: Programming Language :: Python :: 3 :: Only
Classifier: Programming Language :: Python :: 3.8
Classifier: Topic :: Internet :: WWW/HTTP
Classifier: Topic :: Internet :: WWW/HTTP :: Dynamic Content
Requires-Python: >=3.8
Requires-Dist: Django (>=3.2)
Requires-Dist: gunicorn (>=20.0.4)
Requires-Dist: requests (>=2.24.0)
Requires-Dist: discord.py (>=1.5.1)
Requires-Dist: opuslib (>=3.0.1)
Requires-Dist: ffmpeg (>=1.4)
Requires-Dist: fuzzywuzzy[speedup] (>=0.18.0)
Requires-Dist: youtube-dl (>=2020.9.6)
Requires-Dist: rich (>=9.0.1)
Requires-Dist: tqdm (>=4.43.0)
Requires-Dist: dnspython (>=2.0.0)
